fastapi_async_safe/__init__.py
fastapi_async_safe/decorators.py
fastapi_async_safe/dependencies.py
fastapi_async_safe/ext.py
fastapi_async_safe/markers.py
fastapi_async_safe/py.typed
fastapi_async_safe/types.py
fastapi_async_safe_dependencies-0.1.1.dist-info/LICENSE
fastapi_async_safe_dependencies-0.1.1.dist-info/METADATA
fastapi_async_safe_dependencies-0.1.1.dist-info/WHEEL
fastapi_async_safe_dependencies-0.1.1.dist-info/RECORD
