Metadata-Version: 2.1
Name: fastapi-async-safe-dependencies
Version: 0.1.1
Summary: FastAPI async safe dependencies
Home-page: https://github.com/uriyyo/fastapi-async-safe-dependencies
License: MIT
Author: Yurii Karabas
Author-email: 1998uriyyo@gmail.com
Requires-Python: >=3.9,<4.0
Classifier: License :: OSI Approved :: MIT License
Classifier: Operating System :: OS Independent
Classifier: Programming Language :: Python
Classifier: Programming Language :: Python :: 3
Classifier: Programming Language :: Python :: 3.9
Classifier: Programming Language :: Python :: 3.10
Classifier: Programming Language :: Python :: 3.11
Classifier: Programming Language :: Python :: 3.12
Classifier: Programming Language :: Python :: 3 :: Only
Requires-Dist: fastapi (>=0.109.0,<0.110.0)
Requires-Dist: typing-extensions (>=4.9.0,<5.0.0)
Project-URL: Repository, https://github.com/uriyyo/fastapi-async-safe-dependencies
